ytils/__doc__.py
ytils/__init__.py
ytils/converters.py
ytils/dotenv.py
ytils/json.py
ytils/logger.py
ytils/obfuscator.py
ytils/perfomance.py
ytils/printer.py
ytils/reg_exp.py
ytils/sorters.py
ytils/threads.py
ytils/web.py
ytils-0.0.3.dist-info/LICENCE.txt
ytils-0.0.3.dist-info/METADATA
ytils-0.0.3.dist-info/WHEEL
ytils-0.0.3.dist-info/top_level.txt
ytils-0.0.3.dist-info/RECORD
