Metadata-Version: 2.2
Name: ytils
Version: 0.0.3
Summary: Private utils package
Author-email: Roman Smolnyk <poma23324@gmail.com>
Project-URL: Homepage, https://gitlab.com/roman-smolnyk/python-roman-utils
Keywords: private,utils
Classifier: Programming Language :: Python :: 3
Classifier: License :: OSI Approved :: MIT License
Classifier: Operating System :: OS Independent
License-File: LICENCE.txt
